Workbook

Sheet Cover
B2: Danone (Euronext Paris : BN) - DCF à 2 étages
B3: Exercice personnel de valorisation - Yvann Ahoure
B4: Toutes les valeurs sont en millions d'euros (M€), sauf mention contraire.
B6: Sommaire
B8: Dashboard | C8: Synthèse : valeur implicite, écart au marché, sensibilités, contrôles
B9: Assumptions | C9: Hypothèses de projection, WACC (CAPM) et données de marché
B10: Financials | C10: Compte de résultat et flux de trésorerie simplifiés, FY2023-FY2025
B11: DCF | C11: DCF à 2 étages : FCF explicite 5 ans + valeur terminale
B12: Sensitivity | C12: Sensibilité de la valeur par action au WACC et à la croissance terminale
B13: Checks | C13: Contrôles de cohérence du modèle
B16: Sources
B17: - Danone, communiqué de résultats annuels FY2025 "2025: Another year of strong delivery" (20/02/2026).
B18: - Danone, document de consensus analystes Q2/H1 FY2026 (danone.com/investors, 16 analystes).
B19: - Boursorama (cours, capitalisation) - relevé le 12/10/2026.
B20: - stockanalysis.com et valueinvesting.io (bêta, comparables WACC) - relevés le 12/10/2026.
B21: - tradingeconomics.com (taux souverain français à 10 ans, OAT) - relevé le 12/10/2026.
B22: - marketscreener.com (multiples EV/EBITDA Nestlé, Unilever, General Mills) - relevé oct. 2026.
B24: Avertissement : hypothèses de projection (au-delà du consensus 2026), prime de risque actions et croissance terminale sont des estimations personnelles, clairement identifiées comme telles dans l'onglet Assumptions. N'importe quelle incohérence de source (ex. dette nette, bêta) est signalée explicitement plutôt que lissée.

Sheet Dashboard
B2: Dashboard - Danone (EPA : BN)
B3: Toutes les valeurs sont en millions d'euros (M€), sauf mention contraire.
B5: RÉSULTATS CLÉS
B6: Valeur implicite par action (DCF) | D6: =DCF!C21 -> 84.121205
B7: Cours de marché actuel | D7: =DCF!C22 -> 59.5
B8: Écart DCF vs marché | D8: =DCF!C23 -> 0.41380177
B9: Valeur d'entreprise (EV) | D9: =DCF!C17 -> 65913.766
B10: Valeur des fonds propres | D10: =DCF!C19 -> 57483.766
B11: WACC retenu | D11: =Assumptions!C27 -> 0.069250733
B12: Croissance terminale | D12: =Assumptions!C28 -> 0.02
B13: VE/EBITDA implicite du DCF | D13: =DCF!C24 -> 15.346628
B14: VE/EBITDA de marché (calculé) | D14: =DCF!C25 -> 11.429336
B17: COMPARABLES BOURSIERS (CONTEXTE) | E17: marketscreener.com, oct. 2026
B18: Danone (VE/EBITDA de marché, calculé) | D18: =DCF!C25 -> 11.429336
B19: Nestlé (FY2025) | D19: 14.1
B20: Unilever (FY2025) | D20: 12.7
B21: General Mills (FY2026, année fiscale mai) | D21: 9.25
B24: CONTRÔLES DU MODÈLE
B25: Voir le détail des contrôles | D25: =Checks!C25 -> Tous les contrôles sont OK

Sheet Assumptions
B2: Hypothèses
B3: Toutes les valeurs sont en millions d'euros (M€), sauf mention contraire.
B5: DONNÉES DE DÉPART (FY2025, exercice clos le 31/12/2025)
B6: Chiffre d'affaires net FY2025 | C6: 27283 | E6: Communiqué FY2025, 20/02/2026
B7: Free cash-flow FY2025 (communiqué par la société) | C7: 2799 | E7: Communiqué FY2025
B8: Résultat opérationnel courant FY2025 | C8: 3665 | E8: Communiqué FY2025 (marge 13,4 %)
B9: EBITDA FY2025 (calculé : résultat opérationnel + D&A) | C9: 4295 | E9: Calcul perso ; Danone ne publie pas l'EBITDA en ligne dédiée
B10: Dette financière nette FY2025 | C10: 8430 | E10: Communiqué FY2025 ; fourchette des sources 8 059-8 547 M€, voir note
B11: Cours de l'action (12/10/2026) | C11: 59.5 | E11: Boursorama
B12: Capitalisation boursière (12/10/2026) | C12: 40659 | E12: Boursorama
B13: Bêta retenu (ajusté) | C13: 0.56 | E13: valueinvesting.io ; stockanalysis.com affiche 0,20 (écarté, hors norme)
B14: Actions en circulation (calculé = capitalisation / cours, M) | C14: =C12/C11 -> 683.34454 | E14: Base cohérente avec la capitalisation ; diffère du nombre moyen pondéré dilué (645 M) utilisé pour l'EPS
B17: WACC - MÉTHODE CAPM
B18: Taux sans risque (OAT France 10 ans) | C18: 0.049 | E18: tradingeconomics.com - niveau élevé pour une dette souveraine ; voir note ci-dessous
B19: Prime de risque actions (ERP) | C19: 0.05 | E19: Hypothèse standard de marché (type Damodaran), non sourcée spécifiquement
B20: Bêta retenu | C20: 0.56 | E20: valueinvesting.io (ajusté)
B21: Coût de la dette avant impôt | C21: 0.0425 | E21: valueinvesting.io (estimation, aucune émission récente identifiée)
B22: Taux d'IS France | C22: 0.25 | E22: Taux normal de l'impôt sur les sociétés en France
B23: Coût des fonds propres (CAPM) | C23: =C18+C20*C19 -> 0.077
B24: Coût de la dette après impôt | C24: =C21*(1-C22) -> 0.031875
B25: Poids des fonds propres (E / (E+D)) | C25: =C12/(C12+C10) -> 0.8282711
B26: Poids de la dette (D / (E+D)) | C26: =C10/(C12+C10) -> 0.1717289
B27: WACC | C27: =C25*C23+C26*C24 -> 0.069250733
B28: Croissance terminale | C28: 0.02 | E28: Hypothèse personnelle, cohérente avec une croissance nominale long terme en zone euro
B30: Note sur le taux sans risque : l'OAT française à 10 ans se traite début octobre 2026 autour de 4,9 %, un niveau historiquement élevé (risque souverain/budgétaire) plutôt qu'un taux sans risque "propre". Le garder tel quel est prudent (WACC plus élevé, valorisation plus conservatrice) ; un taux allemand (Bund 10 ans) donnerait un WACC et une valeur implicite plus hauts.
B35: TRAJECTOIRE DE CROISSANCE (hypothèses personnelles au-delà de 2026)
B36: Année | C36: 2026 | D36: 2027 | E36: 2028 | F36: 2029 | G36: 2030
B37: Croissance du chiffre d'affaires (%) | C37: 0.03 | D37: 0.035 | E37: 0.035 | F37: 0.03 | G37: 0.025
B38: Marge de free cash-flow (%) | C38: 0.103 | D38: 0.105 | E38: 0.107 | F38: 0.11 | G38: 0.112
B40: 2026 : guidance société (ventes LFL +3 % à +5 %) et consensus analystes (croissance publiée médiane +3,0 %).
B41: 2027-2028 : hypothèse personnelle au milieu de la fourchette de guidance (+3,5 %).
B42: 2029-2030 : ralentissement progressif vers la croissance terminale.
B43: Marge de FCF : hypothèse personnelle d'amélioration progressive, cohérente avec la guidance "résultat opérationnel courant croît plus vite que les ventes". FY2025 réel = 10,3 % (2 799 / 27 283).

Sheet Financials
B2: Compte de résultat et flux de trésorerie simplifiés
B3: Toutes les valeurs sont en millions d'euros (M€), sauf mention contraire.
B5: COMPTE DE RÉSULTAT
C6: FY2023A | D6: FY2024A | E6: FY2025A
B7: Chiffre d'affaires net | C7: 27622 | D7: 27376 | E7: 27283
B8: Résultat opérationnel courant | C8: 3351 | D8: 3514 | E8: 3665
B9: Résultat net, part du Groupe | C9: 2998 | D9: 2021 | E9: 1825
B10: Marge opérationnelle courante (%) | C10: =C8/C7 -> 0.12131634 | D10: =D8/D7 -> 0.12836061 | E10: =E8/E7 -> 0.13433273
B13: FLUX DE TRÉSORERIE
C14: FY2023A | D14: FY2024A | E14: FY2025A
B15: Free cash-flow (communiqué par la société) | C15: 2600 | D15: 3004 | E15: 2799
B16: Marge de FCF (%) | C16: =C15/C7 -> 0.094127869 | D16: =D15/D7 -> 0.10973115 | E16: =E15/E7 -> 0.10259136
B19: Source : communiqués de résultats annuels Danone FY2023 (févr. 2024), FY2024 (févr. 2025) et FY2025 (20/02/2026). Le FY2024 figurant ici est la base de comparaison republiée dans le communiqué FY2025 (27 376 M€), qui peut différer légèrement du chiffre publié à l'origine en 2025 du fait de reclassements mineurs.

Sheet DCF
B2: DCF à 2 étages
B3: Toutes les valeurs sont en millions d'euros (M€), sauf mention contraire.
C5: 2026 | D5: 2027 | E5: 2028 | F5: 2029 | G5: 2030
B6: Chiffre d'affaires | C6: =Assumptions!$C$6*(1+Assumptions!C37) -> 28101.49 | D6: =C6*(1+Assumptions!D37) -> 29085.042 | E6: =D6*(1+Assumptions!E37) -> 30103.019 | F6: =E6*(1+Assumptions!F37) -> 31006.109 | G6: =F6*(1+Assumptions!G37) -> 31781.262
B7: Marge de FCF (%) | C7: =Assumptions!C38 -> 0.103 | D7: =Assumptions!D38 -> 0.105 | E7: =Assumptions!E38 -> 0.107 | F7: =Assumptions!F38 -> 0.11 | G7: =Assumptions!G38 -> 0.112
B8: Free cash-flow | C8: =C6*C7 -> 2894.4535 | D8: =D6*D7 -> 3053.9294 | E8: =E6*E7 -> 3221.023 | F8: =F6*F7 -> 3410.672 | G8: =G6*G7 -> 3559.5013
B10: Facteur d'actualisation | C10: =1/(1+Assumptions!$C$27)^1 -> 0.93523434 | D10: =1/(1+Assumptions!$C$27)^2 -> 0.87466326 | E10: =1/(1+Assumptions!$C$27)^3 -> 0.81801512 | F10: =1/(1+Assumptions!$C$27)^4 -> 0.76503583 | G10: =1/(1+Assumptions!$C$27)^5 -> 0.71548777
B11: VA du free cash-flow | C11: =C8*C10 -> 2706.9923 | D11: =D8*D10 -> 2671.1599 | E11: =E8*E10 -> 2634.8455 | F11: =F8*F10 -> 2609.2863 | G11: =G8*G10 -> 2546.7797
B13: VALEUR D'ENTREPRISE ET VALEUR DES FONDS PROPRES
B14: Somme des VA du FCF explicite (2026-2030) | C14: =SUM(C11:G11) -> 13169.064
B15: Valeur terminale (Gordon growth, non actualisée) | C15: =G8*(1+Assumptions!$C$28)/(Assumptions!$C$27-Assumptions!$C$28) -> 73718.524
B16: VA de la valeur terminale | C16: =C15*G10 -> 52744.702
B17: Valeur d'entreprise (EV) | C17: =C14+C16 -> 65913.766
B18: - Dette financière nette | C18: =Assumptions!C10 -> 8430
B19: -> Valeur des fonds propres | C19: =C17-C18 -> 57483.766
B20: / Actions en circulation (M) | C20: =Assumptions!C14 -> 683.34454
B21: -> Valeur implicite par action | C21: =C19/C20 -> 84.121205
B22: Cours de marché actuel | C22: =Assumptions!C11 -> 59.5
B23: Écart DCF vs marché (%) | C23: =C21/C22-1 -> 0.41380177
B24: VE/EBITDA implicite du DCF | C24: =C17/Assumptions!C9 -> 15.346628
B25: VE/EBITDA de marché (calculé) | C25: =(Assumptions!C12+Assumptions!C10)/Assumptions!C9 -> 11.429336
B27: Lecture : le DCF ressort nettement au-dessus du cours de marché (écart positif), avec un multiple VE/EBITDA implicite plus proche de celui des grands comparables mondiaux (Nestlé ~14x, Unilever ~13x, voir onglet Checks) que le multiple de marché actuel de Danone. Point de prudence : le taux sans risque utilisé (OAT France, ~4,9 %) est élevé par rapport à sa moyenne longue, ce qui tend plutôt à réduire la valeur implicite - l'écart constaté n'est donc pas un artefact d'un WACC trop bas.

Sheet Sensitivity
B2: Sensibilité - valeur implicite par action (€)
B4: WACC \ g terminale | C4: 0.015 | D4: 0.0175 | E4: 0.02 | F4: 0.0225
B5: 0.055 | C5: =(SUMPRODUCT(DCF!$C$8:$G$8,1/(1+$B5)^{1,2,3,4,5})+DCF!$G$8*(1+C$4)/($B5-C$4)/(1+$B5)^5-Assumptions!$C$10)/Assumptions!$C$14 -> 108.8555 | D5: =(SUMPRODUCT(DCF!$C$8:$G$8,1/(1+$B5)^{1,2,3,4,5})+DCF!$G$8*(1+D$4)/($B5-D$4)/(1+$B5)^5-Assumptions!$C$10)/Assumptions!$C$14 -> 115.86341 | E5: =(SUMPRODUCT(DCF!$C$8:$G$8,1/(1+$B5)^{1,2,3,4,5})+DCF!$G$8*(1+E$4)/($B5-E$4)/(1+$B5)^5-Assumptions!$C$10)/Assumptions!$C$14 -> 123.87245 | F5: =(SUMPRODUCT(DCF!$C$8:$G$8,1/(1+$B5)^{1,2,3,4,5})+DCF!$G$8*(1+F$4)/($B5-F$4)/(1+$B5)^5-Assumptions!$C$10)/Assumptions!$C$14 -> 133.11364
B6: 0.06 | C6: =(SUMPRODUCT(DCF!$C$8:$G$8,1/(1+$B6)^{1,2,3,4,5})+DCF!$G$8*(1+C$4)/($B6-C$4)/(1+$B6)^5-Assumptions!$C$10)/Assumptions!$C$14 -> 95.23635 | D6: =(SUMPRODUCT(DCF!$C$8:$G$8,1/(1+$B6)^{1,2,3,4,5})+DCF!$G$8*(1+D$4)/($B6-D$4)/(1+$B6)^5-Assumptions!$C$10)/Assumptions!$C$14 -> 100.62977 | E6: =(SUMPRODUCT(DCF!$C$8:$G$8,1/(1+$B6)^{1,2,3,4,5})+DCF!$G$8*(1+E$4)/($B6-E$4)/(1+$B6)^5-Assumptions!$C$10)/Assumptions!$C$14 -> 106.69738 | F6: =(SUMPRODUCT(DCF!$C$8:$G$8,1/(1+$B6)^{1,2,3,4,5})+DCF!$G$8*(1+F$4)/($B6-F$4)/(1+$B6)^5-Assumptions!$C$10)/Assumptions!$C$14 -> 113.57399
B7: 0.065 | C7: =(SUMPRODUCT(DCF!$C$8:$G$8,1/(1+$B7)^{1,2,3,4,5})+DCF!$G$8*(1+C$4)/($B7-C$4)/(1+$B7)^5-Assumptions!$C$10)/Assumptions!$C$14 -> 84.343527 | D7: =(SUMPRODUCT(DCF!$C$8:$G$8,1/(1+$B7)^{1,2,3,4,5})+DCF!$G$8*(1+D$4)/($B7-D$4)/(1+$B7)^5-Assumptions!$C$10)/Assumptions!$C$14 -> 88.605664 | E7: =(SUMPRODUCT(DCF!$C$8:$G$8,1/(1+$B7)^{1,2,3,4,5})+DCF!$G$8*(1+E$4)/($B7-E$4)/(1+$B7)^5-Assumptions!$C$10)/Assumptions!$C$14 -> 93.341372 | F7: =(SUMPRODUCT(DCF!$C$8:$G$8,1/(1+$B7)^{1,2,3,4,5})+DCF!$G$8*(1+F$4)/($B7-F$4)/(1+$B7)^5-Assumptions!$C$10)/Assumptions!$C$14 -> 98.634221
B8: 0.069 | C8: =(SUMPRODUCT(DCF!$C$8:$G$8,1/(1+$B8)^{1,2,3,4,5})+DCF!$G$8*(1+C$4)/($B8-C$4)/(1+$B8)^5-Assumptions!$C$10)/Assumptions!$C$14 -> 77.083274 | D8: =(SUMPRODUCT(DCF!$C$8:$G$8,1/(1+$B8)^{1,2,3,4,5})+DCF!$G$8*(1+D$4)/($B8-D$4)/(1+$B8)^5-Assumptions!$C$10)/Assumptions!$C$14 -> 80.669005 | E8: =(SUMPRODUCT(DCF!$C$8:$G$8,1/(1+$B8)^{1,2,3,4,5})+DCF!$G$8*(1+E$4)/($B8-E$4)/(1+$B8)^5-Assumptions!$C$10)/Assumptions!$C$14 -> 84.620626 | F8: =(SUMPRODUCT(DCF!$C$8:$G$8,1/(1+$B8)^{1,2,3,4,5})+DCF!$G$8*(1+F$4)/($B8-F$4)/(1+$B8)^5-Assumptions!$C$10)/Assumptions!$C$14 -> 88.997153
B9: 0.07 | C9: =(SUMPRODUCT(DCF!$C$8:$G$8,1/(1+$B9)^{1,2,3,4,5})+DCF!$G$8*(1+C$4)/($B9-C$4)/(1+$B9)^5-Assumptions!$C$10)/Assumptions!$C$14 -> 75.433435 | D9: =(SUMPRODUCT(DCF!$C$8:$G$8,1/(1+$B9)^{1,2,3,4,5})+DCF!$G$8*(1+D$4)/($B9-D$4)/(1+$B9)^5-Assumptions!$C$10)/Assumptions!$C$14 -> 78.874021 | E9: =(SUMPRODUCT(DCF!$C$8:$G$8,1/(1+$B9)^{1,2,3,4,5})+DCF!$G$8*(1+E$4)/($B9-E$4)/(1+$B9)^5-Assumptions!$C$10)/Assumptions!$C$14 -> 82.658665 | F9: =(SUMPRODUCT(DCF!$C$8:$G$8,1/(1+$B9)^{1,2,3,4,5})+DCF!$G$8*(1+F$4)/($B9-F$4)/(1+$B9)^5-Assumptions!$C$10)/Assumptions!$C$14 -> 86.841692
B10: 0.075 | C10: =(SUMPRODUCT(DCF!$C$8:$G$8,1/(1+$B10)^{1,2,3,4,5})+DCF!$G$8*(1+C$4)/($B10-C$4)/(1+$B10)^5-Assumptions!$C$10)/Assumptions!$C$14 -> 68.010344 | D10: =(SUMPRODUCT(DCF!$C$8:$G$8,1/(1+$B10)^{1,2,3,4,5})+DCF!$G$8*(1+D$4)/($B10-D$4)/(1+$B10)^5-Assumptions!$C$10)/Assumptions!$C$14 -> 70.836763 | E10: =(SUMPRODUCT(DCF!$C$8:$G$8,1/(1+$B10)^{1,2,3,4,5})+DCF!$G$8*(1+E$4)/($B10-E$4)/(1+$B10)^5-Assumptions!$C$10)/Assumptions!$C$14 -> 73.920129 | F10: =(SUMPRODUCT(DCF!$C$8:$G$8,1/(1+$B10)^{1,2,3,4,5})+DCF!$G$8*(1+F$4)/($B10-F$4)/(1+$B10)^5-Assumptions!$C$10)/Assumptions!$C$14 -> 77.297148
B11: 0.08 | C11: =(SUMPRODUCT(DCF!$C$8:$G$8,1/(1+$B11)^{1,2,3,4,5})+DCF!$G$8*(1+C$4)/($B11-C$4)/(1+$B11)^5-Assumptions!$C$10)/Assumptions!$C$14 -> 61.731056 | D11: =(SUMPRODUCT(DCF!$C$8:$G$8,1/(1+$B11)^{1,2,3,4,5})+DCF!$G$8*(1+D$4)/($B11-D$4)/(1+$B11)^5-Assumptions!$C$10)/Assumptions!$C$14 -> 64.087196 | E11: =(SUMPRODUCT(DCF!$C$8:$G$8,1/(1+$B11)^{1,2,3,4,5})+DCF!$G$8*(1+E$4)/($B11-E$4)/(1+$B11)^5-Assumptions!$C$10)/Assumptions!$C$14 -> 66.639681 | F11: =(SUMPRODUCT(DCF!$C$8:$G$8,1/(1+$B11)^{1,2,3,4,5})+DCF!$G$8*(1+F$4)/($B11-F$4)/(1+$B11)^5-Assumptions!$C$10)/Assumptions!$C$14 -> 69.414121
B14: Formule : somme des FCF actualisés sur la trajectoire de l'onglet DCF + valeur terminale (Gordon growth) au couple (WACC, g), moins la dette nette, divisé par le nombre d'actions.

Sheet Checks
B2: Contrôles de cohérence du modèle
B5: Contrôle | D5: Résultat
B6: Croissance terminale < WACC (sinon valeur terminale indéfinie) | D6: =IF(Assumptions!C28<Assumptions!C27,"OK","A VERIFIER") -> OK
B7: Poids E/V + D/V = 100 % | D7: =IF(ROUND(Assumptions!C25+Assumptions!C26,4)=1,"OK","A VERIFIER") -> OK
B8: Toutes les marges de FCF projetées sont strictement positives | D8: =IF(MIN(Assumptions!C38:G38)>0,"OK","A VERIFIER") -> OK
B9: VE recalculée (somme VA FCF + VA valeur terminale) = DCF!C17 | D9: =IF(ROUND(DCF!C14+DCF!C16-DCF!C17,1)=0,"OK","A VERIFIER") -> OK
B10: Actions en circulation cohérentes avec la capitalisation (à 1 % près) | D10: =IF(ABS(Assumptions!C14*Assumptions!C11/Assumptions!C12-1)<0.01,"OK","A VERIFIER") -> OK
B11: Valeur des fonds propres positive | D11: =IF(DCF!C19>0,"OK","A VERIFIER") -> OK
B25: Synthèse | C25: =IF(COUNTIF(D6:D11,"OK")=6,"Tous les contrôles sont OK","Au moins un contrôle à vérifier") -> Tous les contrôles sont OK
B28: Note : ces contrôles vérifient la cohérence interne du modèle (pas d'erreur de construction), pas la justesse des hypothèses elles-mêmes. Les hypothèses de croissance et de marge restent des choix personnels, documentés et sourcés dans l'onglet Assumptions.
