Workbook

Sheet Cover
B2: Groupe Sonatel (BRVM : SNTS) - Modèle DCF et comparables
B3: Exercice personnel de valorisation - Yvann Ahoure
B5: Sommaire
B6: 1. Assumptions
B7: 2. DCF
B8: 3. Sensitivity
B9: 4. Comps
B10: 5. Checks
B11: Avertissement
B12: Exercice personnel réalisé à partir de données publiques (sources citées dans l'onglet Assumptions), à but de démonstration méthodologique. Ne constitue pas une recommandation d'investissement. Le free cash-flow 2025 est utilisé comme proxy simplifié du FCFF ; la dette nette n'est pas disponible publiquement à cette maille et n'est donc pas déduite de la valeur d'entreprise.

Sheet Assumptions
B2: Assumptions - Groupe Sonatel
B3: Toutes les valeurs en Md FCFA sauf mention contraire
B5: Données de départ (FY2025, réel)
B6: Chiffre d'affaires 2025 | E6: 1923.1
B7: EBITDAaL 2025 | E7: 921.2
B8: Free cash-flow 2025 (proxy FCFF) | E8: 422
B9: Nombre d'actions (millions) | E9: 100
B10: Capitalisation boursière (Md FCFA) | E10: 4498
B12: Ratios dérivés
B13: Marge d'EBITDAaL 2025 | E13: =E7/E6 -> 0.47901825
B14: Marge de FCF 2025 | E14: =E8/E6 -> 0.21943737
B15: Cours de marché implicite (FCFA/action) | E15: =E10*1000/E9 -> 44980
B17: Hypothèses de projection 2026-2030
C18: 2026 | D18: 2027 | E18: 2028 | F18: 2029 | G18: 2030
B19: Croissance du chiffre d'affaires | C19: 0.07 | D19: 0.06 | E19: 0.05 | F19: 0.045 | G19: 0.04
B20: Marge de FCF (% du CA, maintenue constante) | C20: =$E$14 -> 0.21943737 | D20: =C20 -> 0.21943737 | E20: =C20 -> 0.21943737 | F20: =C20 -> 0.21943737 | G20: =C20 -> 0.21943737
B22: WACC et croissance terminale
B23: WACC retenu | E23: 0.11
B24: Croissance terminale (g) | E24: 0.03
B26: Sources
B27: - CA, EBITDAaL, FCF 2025 : communiqué Sonatel "Résultats consolidés au 31 décembre 2025" (sonatel.sn)
B28: - Capitalisation, nombre d'actions : Sikafinance, fiche société SNTS.sn
B29: - Comparable Maroc Telecom (EV/EBITDA) : Multiples.vc, 12 octobre 2026
B30: - Hypothèses de croissance 2026-2030, WACC et g terminale : estimations personnelles (non sourcées, posées pour l'exercice)

Sheet DCF
B2: DCF - Groupe Sonatel
B3: Md FCFA sauf mention contraire
C5: 2026 | D5: 2027 | E5: 2028 | F5: 2029 | G5: 2030
B6: Croissance du CA | C6: =Assumptions!C19 -> 0.07 | D6: =Assumptions!D19 -> 0.06 | E6: =Assumptions!E19 -> 0.05 | F6: =Assumptions!F19 -> 0.045 | G6: =Assumptions!G19 -> 0.04
B7: Chiffre d'affaires | C7: =Assumptions!$E$6*(1+C6) -> 2057.717 | D7: =C7*(1+D6) -> 2181.18 | E7: =D7*(1+E6) -> 2290.239 | F7: =E7*(1+F6) -> 2393.2998 | G7: =F7*(1+G6) -> 2489.0318
B8: Marge de FCF | C8: =Assumptions!C20 -> 0.21943737 | D8: =Assumptions!D20 -> 0.21943737 | E8: =Assumptions!E20 -> 0.21943737 | F8: =Assumptions!F20 -> 0.21943737 | G8: =Assumptions!G20 -> 0.21943737
B9: Free cash-flow (FCFF proxy) | C9: =C7*C8 -> 451.54 | D9: =D7*D8 -> 478.6324 | E9: =E7*E8 -> 502.56402 | F9: =F7*F8 -> 525.1794 | G9: =G7*G8 -> 546.18658
B10: Période d'actualisation (n, convention mid-year) | C10: 0.5 | D10: 1.5 | E10: 2.5 | F10: 3.5 | G10: 4.5
B11: Facteur d'actualisation | C11: =1/(1+Assumptions!$E$23)^C10 -> 0.949158 | D11: =1/(1+Assumptions!$E$23)^D10 -> 0.85509729 | E11: =1/(1+Assumptions!$E$23)^E10 -> 0.77035792 | F11: =1/(1+Assumptions!$E$23)^F10 -> 0.69401615 | G11: =1/(1+Assumptions!$E$23)^G10 -> 0.62523977
B12: VA des flux explicites | C12: =C9*C11 -> 428.5828 | D12: =D9*D11 -> 409.27727 | E12: =E9*E11 -> 387.15417 | F12: =F9*F11 -> 364.48298 | G12: =G9*G11 -> 341.49757
B14: Somme des VA des flux explicites (2026-2030) | C14: =SUM(C12:G12) -> 1930.9948
B16: Valeur terminale (Gordon Growth, fin 2030) | C16: =G9*(1+Assumptions!$E$24)/(Assumptions!$E$23-Assumptions!$E$24) -> 7032.1522
B17: VA de la valeur terminale | C17: =C16*G11 -> 4396.7812
B19: Valeur d'entreprise implicite (EV) | C19: =C14+C17 -> 6327.776
B20: Part de la valeur terminale dans l'EV | C20: =C17/C19 -> 0.69483831 | I20: VE implicite (DCF) | J20: =C23 -> 63277.76
I21: Cours de marché | J21: =C24 -> 44980
B22: Nombre d'actions (millions) | C22: =Assumptions!E9 -> 100
B23: VE implicite par action (FCFA) | C23: =C19*1000/C22 -> 63277.76
B24: Cours de marché, pour mémoire (FCFA) | C24: =Assumptions!E15 -> 44980
B27: Lecture : la dette nette de Sonatel n'est pas publiée à une maille fiable (voir Assumptions/Cover). Les deux lignes ci-dessus comparent donc une VE implicite du DCF à un cours de marché (capitalisation), et non une valeur des fonds propres à une valeur des fonds propres : aucune conclusion de potentiel de hausse ou de baisse n'en est tirée.
B32: RECOUPEMENT DE LA VALEUR TERMINALE (MULTIPLE DE SORTIE)
B33: Marge d'EBITDAaL (hypothèse de projection) | C33: =Assumptions!E13 -> 0.47901825
B34: EBITDAaL implicite, année 5 (2030, Md FCFA) | C34: =G7*C33 -> 1192.2916
B35: Multiple de sortie implicite (VT / EBITDAaL an 5) | C35: =C16/C34 -> 5.8980135
B36: Comparable Maroc Telecom (pour mémoire) | C36: =Comps!D7 -> 4.9
B38: Lecture : ce recoupement applique la méthode des multiples de sortie en complément de la méthode Gordon growth (cf. guide BIWS, Key Rule #4) : on reconvertit la valeur terminale obtenue par Gordon growth en un multiple implicite VE/EBITDAaL à l'année 5, à comparer avec le comparable régional déjà retenu (onglet Comps, Maroc Telecom). La marge d'EBITDAaL à l'année 5 reprend l'hypothèse de marge constante déjà utilisée pour le free cash-flow dans l'onglet Assumptions.

Sheet Sensitivity
B2: Sensibilité - VE implicite par action (FCFA, indicatif)
B3: Variation du WACC et de la croissance terminale (g)
B5: WACC \ g | C5: 0.02 | D5: 0.025 | E5: 0.03 | F5: 0.035
B6: 0.095 | C6: =(SUMPRODUCT(DCF!$C$9:$G$9,1/(1+$B6)^DCF!$C$10:$G$10)+DCF!$G$9*(1+C$5)/($B6-C$5)/(1+$B6)^DCF!$G$10)*1000/DCF!$C$22 -> 69326.978 | D6: =(SUMPRODUCT(DCF!$C$9:$G$9,1/(1+$B6)^DCF!$C$10:$G$10)+DCF!$G$9*(1+D$5)/($B6-D$5)/(1+$B6)^DCF!$G$10)*1000/DCF!$C$22 -> 73113.167 | E6: =(SUMPRODUCT(DCF!$C$9:$G$9,1/(1+$B6)^DCF!$C$10:$G$10)+DCF!$G$9*(1+E$5)/($B6-E$5)/(1+$B6)^DCF!$G$10)*1000/DCF!$C$22 -> 77481.847 | F6: =(SUMPRODUCT(DCF!$C$9:$G$9,1/(1+$B6)^DCF!$C$10:$G$10)+DCF!$G$9*(1+F$5)/($B6-F$5)/(1+$B6)^DCF!$G$10)*1000/DCF!$C$22 -> 82578.64
B7: 0.1 | C7: =(SUMPRODUCT(DCF!$C$9:$G$9,1/(1+$B7)^DCF!$C$10:$G$10)+DCF!$G$9*(1+C$5)/($B7-C$5)/(1+$B7)^DCF!$G$10)*1000/DCF!$C$22 -> 65083.865 | D7: =(SUMPRODUCT(DCF!$C$9:$G$9,1/(1+$B7)^DCF!$C$10:$G$10)+DCF!$G$9*(1+D$5)/($B7-D$5)/(1+$B7)^DCF!$G$10)*1000/DCF!$C$22 -> 68344.374 | E7: =(SUMPRODUCT(DCF!$C$9:$G$9,1/(1+$B7)^DCF!$C$10:$G$10)+DCF!$G$9*(1+E$5)/($B7-E$5)/(1+$B7)^DCF!$G$10)*1000/DCF!$C$22 -> 72070.669 | F7: =(SUMPRODUCT(DCF!$C$9:$G$9,1/(1+$B7)^DCF!$C$10:$G$10)+DCF!$G$9*(1+F$5)/($B7-F$5)/(1+$B7)^DCF!$G$10)*1000/DCF!$C$22 -> 76370.241
B8: 0.105 | C8: =(SUMPRODUCT(DCF!$C$9:$G$9,1/(1+$B8)^DCF!$C$10:$G$10)+DCF!$G$9*(1+C$5)/($B8-C$5)/(1+$B8)^DCF!$G$10)*1000/DCF!$C$22 -> 61340.297 | D8: =(SUMPRODUCT(DCF!$C$9:$G$9,1/(1+$B8)^DCF!$C$10:$G$10)+DCF!$G$9*(1+D$5)/($B8-D$5)/(1+$B8)^DCF!$G$10)*1000/DCF!$C$22 -> 64171.911 | E8: =(SUMPRODUCT(DCF!$C$9:$G$9,1/(1+$B8)^DCF!$C$10:$G$10)+DCF!$G$9*(1+E$5)/($B8-E$5)/(1+$B8)^DCF!$G$10)*1000/DCF!$C$22 -> 67381.075 | F8: =(SUMPRODUCT(DCF!$C$9:$G$9,1/(1+$B8)^DCF!$C$10:$G$10)+DCF!$G$9*(1+F$5)/($B8-F$5)/(1+$B8)^DCF!$G$10)*1000/DCF!$C$22 -> 71048.69
B9: 0.11 | C9: =(SUMPRODUCT(DCF!$C$9:$G$9,1/(1+$B9)^DCF!$C$10:$G$10)+DCF!$G$9*(1+C$5)/($B9-C$5)/(1+$B9)^DCF!$G$10)*1000/DCF!$C$22 -> 58013.006 | D9: =(SUMPRODUCT(DCF!$C$9:$G$9,1/(1+$B9)^DCF!$C$10:$G$10)+DCF!$G$9*(1+D$5)/($B9-D$5)/(1+$B9)^DCF!$G$10)*1000/DCF!$C$22 -> 60490.537 | E9: =(SUMPRODUCT(DCF!$C$9:$G$9,1/(1+$B9)^DCF!$C$10:$G$10)+DCF!$G$9*(1+E$5)/($B9-E$5)/(1+$B9)^DCF!$G$10)*1000/DCF!$C$22 -> 63277.76 | F9: =(SUMPRODUCT(DCF!$C$9:$G$9,1/(1+$B9)^DCF!$C$10:$G$10)+DCF!$G$9*(1+F$5)/($B9-F$5)/(1+$B9)^DCF!$G$10)*1000/DCF!$C$22 -> 66436.613
B10: 0.115 | C10: =(SUMPRODUCT(DCF!$C$9:$G$9,1/(1+$B10)^DCF!$C$10:$G$10)+DCF!$G$9*(1+C$5)/($B10-C$5)/(1+$B10)^DCF!$G$10)*1000/DCF!$C$22 -> 55036.254 | D10: =(SUMPRODUCT(DCF!$C$9:$G$9,1/(1+$B10)^DCF!$C$10:$G$10)+DCF!$G$9*(1+D$5)/($B10-D$5)/(1+$B10)^DCF!$G$10)*1000/DCF!$C$22 -> 57218.395 | E10: =(SUMPRODUCT(DCF!$C$9:$G$9,1/(1+$B10)^DCF!$C$10:$G$10)+DCF!$G$9*(1+E$5)/($B10-E$5)/(1+$B10)^DCF!$G$10)*1000/DCF!$C$22 -> 59657.259 | F10: =(SUMPRODUCT(DCF!$C$9:$G$9,1/(1+$B10)^DCF!$C$10:$G$10)+DCF!$G$9*(1+F$5)/($B10-F$5)/(1+$B10)^DCF!$G$10)*1000/DCF!$C$22 -> 62400.981
B11: 0.12 | C11: =(SUMPRODUCT(DCF!$C$9:$G$9,1/(1+$B11)^DCF!$C$10:$G$10)+DCF!$G$9*(1+C$5)/($B11-C$5)/(1+$B11)^DCF!$G$10)*1000/DCF!$C$22 -> 52357.451 | D11: =(SUMPRODUCT(DCF!$C$9:$G$9,1/(1+$B11)^DCF!$C$10:$G$10)+DCF!$G$9*(1+D$5)/($B11-D$5)/(1+$B11)^DCF!$G$10)*1000/DCF!$C$22 -> 54290.863 | E11: =(SUMPRODUCT(DCF!$C$9:$G$9,1/(1+$B11)^DCF!$C$10:$G$10)+DCF!$G$9*(1+E$5)/($B11-E$5)/(1+$B11)^DCF!$G$10)*1000/DCF!$C$22 -> 56439.098 | F11: =(SUMPRODUCT(DCF!$C$9:$G$9,1/(1+$B11)^DCF!$C$10:$G$10)+DCF!$G$9*(1+F$5)/($B11-F$5)/(1+$B11)^DCF!$G$10)*1000/DCF!$C$22 -> 58840.067
B12: 0.125 | C12: =(SUMPRODUCT(DCF!$C$9:$G$9,1/(1+$B12)^DCF!$C$10:$G$10)+DCF!$G$9*(1+C$5)/($B12-C$5)/(1+$B12)^DCF!$G$10)*1000/DCF!$C$22 -> 49934.025 | D12: =(SUMPRODUCT(DCF!$C$9:$G$9,1/(1+$B12)^DCF!$C$10:$G$10)+DCF!$G$9*(1+D$5)/($B12-D$5)/(1+$B12)^DCF!$G$10)*1000/DCF!$C$22 -> 51656.242 | E12: =(SUMPRODUCT(DCF!$C$9:$G$9,1/(1+$B12)^DCF!$C$10:$G$10)+DCF!$G$9*(1+E$5)/($B12-E$5)/(1+$B12)^DCF!$G$10)*1000/DCF!$C$22 -> 53559.745 | F12: =(SUMPRODUCT(DCF!$C$9:$G$9,1/(1+$B12)^DCF!$C$10:$G$10)+DCF!$G$9*(1+F$5)/($B12-F$5)/(1+$B12)^DCF!$G$10)*1000/DCF!$C$22 -> 55674.748
B14: Lecture : la case en surbrillance correspond au scénario central (WACC 11,0 % / g 3,0 %) utilisé dans l'onglet DCF. Valeurs en VE par action (pas de dette nette disponible pour un pont vers les fonds propres).

Sheet Comps
B2: Comparables boursiers - Télécoms
B3: Multiples EV/EBITDA - recoupement avec le DCF
B5: Société | C5: Place de cotation | D5: EV/EBITDA (FY) | E5: Source
B6: Groupe Sonatel (implicite marché) | C6: BRVM (SNTS) | D6: =Assumptions!E10/Assumptions!E7 -> 4.8827616 | E6: Capitalisation / EBITDAaL 2025 (proxy EV, dette nette non disponible)
B7: Maroc Telecom | C7: Euronext / BVC | D7: 4.9 | E7: Multiples.vc, dernier exercice (FY), 12 octobre 2026
B9: Lecture
B10: Le multiple implicite de marché sur Sonatel est proche de celui de Maroc Telecom, ce qui suggère une valorisation de marché cohérente avec les comparables régionaux, même si le DCF (onglet DCF) ressort au-dessus du cours actuel sous les hypothèses retenues.

Sheet Checks
B2: Contrôles de cohérence - Sonatel
B5: Contrôle | D5: Résultat
B6: Croissance terminale (g) < WACC (sinon valeur terminale indéfinie) | D6: =IF(Assumptions!E24<Assumptions!E23,"OK","A VERIFIER") -> OK
B7: Toutes les marges de FCF projetées sont strictement positives | D7: =IF(MIN(Assumptions!C20:G20)>0,"OK","A VERIFIER") -> OK
B8: EV recalculée (somme VA flux + VA valeur terminale) = DCF!C19 | D8: =IF(ROUND(DCF!C14+DCF!C17-DCF!C19,1)=0,"OK","A VERIFIER") -> OK
B9: Cours implicite de marché cohérent (capitalisation × 1000 / actions = Assumptions!E15) | D9: =IF(ROUND(Assumptions!E10*1000/Assumptions!E9-Assumptions!E15,0)=0,"OK","A VERIFIER") -> OK
B10: Valeur d'entreprise implicite positive | D10: =IF(DCF!C19>0,"OK","A VERIFIER") -> OK
B12: Synthèse | C12: =IF(COUNTIF(D6:D13,"OK")=6,"Tous les contrôles sont OK","Au moins un contrôle à vérifier") -> Tous les contrôles sont OK
B13: Multiple de sortie implicite (VT) du même ordre de grandeur que le comparable régional | D13: =IF(AND(DCF!C35>=0.5*DCF!C36,DCF!C35<=2*DCF!C36),"OK","A VERIFIER") -> OK
B15: Note : ces contrôles vérifient la cohérence interne du modèle (pas d'erreur de construction), pas la justesse des hypothèses elles-mêmes.
