Workbook

Sheet Cover
B2: Tesla, Inc. (NASDAQ : TSLA) - DCF à 2 étages sur une valeur de croissance
B3: Exercice personnel de valorisation - Yvann Ahoure
B5: Sommaire
B7: Assumptions | C7: Hypothèses de projection, WACC et données de marché
B8: DCF | C8: DCF à 2 étages (FCF explicite 5 ans + valeur terminale Gordon)
B9: Sensitivity | C9: Sensibilité valeur/action au WACC et à la croissance terminale
B10: Market Gap | C10: Lecture de l'écart entre le DCF et la capitalisation boursière
B13: Sources
B14: Tesla, Form 10-K FY2025 (SEC EDGAR, filed ~27 Jan 2026) ; Tesla Q4/FY2025 shareholder deck (8-K Ex. 99.1, ~28 Jan 2026).
B15: stockanalysis.com (cours, capitalisation, bêta, consensus analystes) - relevé le 12 octobre 2026.
B16: Toutes les hypothèses de projection (croissance au-delà du consensus, marge de FCF, WACC) sont des estimations personnelles, clairement identifiées comme telles ci-dessous.

Sheet Assumptions
B2: Hypothèses
B4: Données de départ (FY2025, année close le 31/12/2025)
B5: Chiffre d'affaires FY2025 ($M) | C5: 94827 | E5: 10-K FY2025 / 8-K Ex.99.1, SEC EDGAR
B6: EBITDA ajusté FY2025 ($M) | C6: 14596 | E6: 8-K Ex.99.1 (non-GAAP, définition société)
B7: Free cash-flow FY2025 ($M) | C7: 6220 | E7: 8-K Ex.99.1 (non-GAAP)
B8: Trésorerie + placements ($M) | C8: 44059 | E8: 10-K FY2025, bilan
B9: Dette totale + leasing financier ($M) | C9: 8376 | E9: 10-K FY2025, bilan
B10: Actions en circulation (M, 23/01/2026) | C10: 3752.4 | E10: 10-K FY2025, page de garde
B11: Cours de l'action (12/10/2026, $) | C11: 379.26 | E11: stockanalysis.com
B12: Capitalisation boursière ($M) | C12: 1500000 | E12: stockanalysis.com (~1,50 T$)
B13: Bêta (régression) | C13: 1.92 | E13: stockanalysis.com
B15: Trésorerie nette ($M) | C15: =C8-C9 -> 35683 | E15: (trésorerie + placements - dette totale)
B18: WACC (construit, méthode CAPM)
B19: Taux sans risque (UST 10 ans) | C19: 0.0415 | E19: stockanalysis.com / marché, oct. 2026
B20: Prime de risque actions (ERP) | C20: 0.05 | E20: Hypothèse standard de marché (prime de risque actions)
B21: Bêta retenu | C21: 1.92 | E21: stockanalysis.com
B22: Coût des fonds propres | C22: =C19+C21*C20 -> 0.1375
B23: WACC retenu (trésorerie nette ⇒ coût de la dette ignoré) | C23: 0.135 | E23: Arrondi prudent du coût des fonds propres ; cellule éditable pour tester d'autres scénarios
B24: Croissance terminale | C24: 0.03 | E24: Hypothèse personnelle, proche de l'inflation/croissance du PIB nominal long terme
B27: Trajectoire de croissance du chiffre d'affaires (hypothèses personnelles)
B28: Année | C28: 2026 | D28: 2027 | E28: 2028 | F28: 2029 | G28: 2030
B29: Croissance du CA (%) | C29: 0.129 | D29: 0.137 | E29: 0.1 | F29: 0.07 | G29: 0.05
B30: Marge de free cash-flow (%) | C30: 0.07 | D30: 0.08 | E30: 0.09 | F30: 0.1 | G30: 0.11
B32: 2026-2027 : consensus analystes (stockanalysis.com, 40 analystes, relevé 12/10/2026).
B33: 2028-2030 : hypothèse personnelle de ralentissement progressif vers un taux proche de la croissance terminale.
B34: Marge de FCF : hypothèse personnelle d'amélioration progressive à mesure que l'intensité du capex (Gigafactories, IA/Optimus) se normalise. FY2025 réel = 6,6 % (6 220 / 94 827).

Sheet DCF
B2: DCF à 2 étages
B4: Année | C4: 2026 | D4: 2027 | E4: 2028 | F4: 2029 | G4: 2030
B5: Chiffre d'affaires ($M) | C5: =Assumptions!$C$5*(1+Assumptions!C29) -> 107059.68 | D5: =C5*(1+Assumptions!D29) -> 121726.86 | E5: =D5*(1+Assumptions!E29) -> 133899.55 | F5: =E5*(1+Assumptions!F29) -> 143272.51 | G5: =F5*(1+Assumptions!G29) -> 150436.14
B6: Marge de FCF (%) | C6: =Assumptions!C30 -> 0.07 | D6: =Assumptions!D30 -> 0.08 | E6: =Assumptions!E30 -> 0.09 | F6: =Assumptions!F30 -> 0.1 | G6: =Assumptions!G30 -> 0.11
B7: Free cash-flow ($M) | C7: =C5*C6 -> 7494.1778 | D7: =D5*D6 -> 9738.1488 | E7: =E5*E6 -> 12050.959 | F7: =F5*F6 -> 14327.251 | G7: =G5*G6 -> 16547.975
B9: Facteur d'actualisation (convention mid-year) | C9: =1/(1+Assumptions!$C$23)^0.5 -> 0.93864651 | D9: =1/(1+Assumptions!$C$23)^1.5 -> 0.82700133 | E9: =1/(1+Assumptions!$C$23)^2.5 -> 0.72863553 | F9: =1/(1+Assumptions!$C$23)^3.5 -> 0.64196963 | G9: =1/(1+Assumptions!$C$23)^4.5 -> 0.56561201
B10: VA du FCF ($M) | C10: =C7*C9 -> 7034.3838 | D10: =D7*D9 -> 8053.462 | E10: =E7*E9 -> 8780.757 | F10: =F7*F9 -> 9197.6603 | G10: =G7*G9 -> 9359.7336
B12: Somme des VA du FCF explicite ($M) | C12: =SUM(C10:G10) -> 42425.997
B14: Valeur terminale (Gordon growth, non actualisée, $M) | C14: =G7*(1+Assumptions!$C$24)/(Assumptions!$C$23-Assumptions!$C$24) -> 162327.76
B15: VA de la valeur terminale ($M) | C15: =C14*G9 -> 91814.53
B17: Valeur d'entreprise (EV, $M) | C17: =C12+C15 -> 134240.53
B18: + Trésorerie nette ($M) | C18: =Assumptions!C15 -> 35683
B19: -> Valeur des fonds propres ($M) | C19: =C17+C18 -> 169923.53
B20: / Actions en circulation (M) | C20: =Assumptions!C10 -> 3752.4
B21: -> Valeur implicite par action ($) | C21: =C19/C20 -> 45.283959
B22: Cours de marché actuel ($) | C22: =Assumptions!C11 -> 379.26
B23: Écart DCF vs marché (%) | C23: =C21/C22-1 -> -0.88059917
B24: VE/EBITDA implicite du DCF (sur EBITDA ajusté FY2025) | C24: =C17/Assumptions!C6 -> 9.1970763
B25: VE/EBITDA impliqué par le marché ((capi - trésorerie nette) / EBITDA FY2025) | C25: =(Assumptions!C12-Assumptions!C15)/Assumptions!C6 -> 100.32317
B27: Lecture : ce DCF, construit uniquement sur les flux de l'activité automobile/énergie actuelle, fait ressortir une valeur par action très inférieure au cours de marché. L'écart ne traduit pas une erreur de calcul mais le fait que la capitalisation de Tesla intègre des paris sur des relais de croissance non reflétés dans les flux actuels (robotaxi/FSD, Optimus, stockage d'énergie) ; voir l'onglet Market Gap.
B32: RECOUPEMENT DE LA VALEUR TERMINALE (MULTIPLE DE SORTIE)
B33: Marge d'EBITDA ajusté FY2025 (hypothèse de projection) | C33: =Assumptions!C6/Assumptions!C5 -> 0.15392241
B34: EBITDA implicite, année 5 (2030, $M) | C34: =G5*C33 -> 23155.493
B35: Multiple de sortie implicite (VT / EBITDA an 5) | C35: =C14/C34 -> 7.0103349
B36: Pour mémoire : multiple implicite du DCF sur EBITDA actuel | C36: =C24 -> 9.1970763
B38: Lecture : ce recoupement applique la méthode des multiples de sortie en complément de la méthode Gordon growth (cf. guide BIWS, Key Rule #4). Aucun comparable boursier (EV/EBITDA) n'étant sourcé dans ce modèle pour un acteur automobile ou technologique comparable à Tesla sur son profil actuel, le multiple de sortie implicite est présenté à titre de contrôle de cohérence interne (il reste dans un ordre de grandeur proche du multiple déjà implicite du DCF sur l'EBITDA actuel), et non comme un recoupement contre des comparables externes.

Sheet Sensitivity
B2: Sensibilité - valeur implicite par action ($)
B4: WACC \ g terminale | C4: 0.02 | D4: 0.025 | E4: 0.03 | F4: 0.035
B5: 0.11 | C5: =(SUMPRODUCT(DCF!$C$7:$G$7,1/(1+$B5)^{0.5,1.5,2.5,3.5,4.5})+DCF!$G$7*(1+C$4)/($B5-C$4)/(1+$B5)^4.5+Assumptions!$C$15)/Assumptions!$C$10 -> 52.754601 | D5: =(SUMPRODUCT(DCF!$C$7:$G$7,1/(1+$B5)^{0.5,1.5,2.5,3.5,4.5})+DCF!$G$7*(1+D$4)/($B5-D$4)/(1+$B5)^4.5+Assumptions!$C$15)/Assumptions!$C$10 -> 54.754987 | E5: =(SUMPRODUCT(DCF!$C$7:$G$7,1/(1+$B5)^{0.5,1.5,2.5,3.5,4.5})+DCF!$G$7*(1+E$4)/($B5-E$4)/(1+$B5)^4.5+Assumptions!$C$15)/Assumptions!$C$10 -> 57.005422 | F5: =(SUMPRODUCT(DCF!$C$7:$G$7,1/(1+$B5)^{0.5,1.5,2.5,3.5,4.5})+DCF!$G$7*(1+F$4)/($B5-F$4)/(1+$B5)^4.5+Assumptions!$C$15)/Assumptions!$C$10 -> 59.555914
B6: 0.12 | C6: =(SUMPRODUCT(DCF!$C$7:$G$7,1/(1+$B6)^{0.5,1.5,2.5,3.5,4.5})+DCF!$G$7*(1+C$4)/($B6-C$4)/(1+$B6)^4.5+Assumptions!$C$15)/Assumptions!$C$10 -> 48.233258 | D6: =(SUMPRODUCT(DCF!$C$7:$G$7,1/(1+$B6)^{0.5,1.5,2.5,3.5,4.5})+DCF!$G$7*(1+D$4)/($B6-D$4)/(1+$B6)^4.5+Assumptions!$C$15)/Assumptions!$C$10 -> 49.794316 | E6: =(SUMPRODUCT(DCF!$C$7:$G$7,1/(1+$B6)^{0.5,1.5,2.5,3.5,4.5})+DCF!$G$7*(1+E$4)/($B6-E$4)/(1+$B6)^4.5+Assumptions!$C$15)/Assumptions!$C$10 -> 51.528825 | F6: =(SUMPRODUCT(DCF!$C$7:$G$7,1/(1+$B6)^{0.5,1.5,2.5,3.5,4.5})+DCF!$G$7*(1+F$4)/($B6-F$4)/(1+$B6)^4.5+Assumptions!$C$15)/Assumptions!$C$10 -> 53.467394
B7: 0.125 | C7: =(SUMPRODUCT(DCF!$C$7:$G$7,1/(1+$B7)^{0.5,1.5,2.5,3.5,4.5})+DCF!$G$7*(1+C$4)/($B7-C$4)/(1+$B7)^4.5+Assumptions!$C$15)/Assumptions!$C$10 -> 46.298605 | D7: =(SUMPRODUCT(DCF!$C$7:$G$7,1/(1+$B7)^{0.5,1.5,2.5,3.5,4.5})+DCF!$G$7*(1+D$4)/($B7-D$4)/(1+$B7)^4.5+Assumptions!$C$15)/Assumptions!$C$10 -> 47.689142 | E7: =(SUMPRODUCT(DCF!$C$7:$G$7,1/(1+$B7)^{0.5,1.5,2.5,3.5,4.5})+DCF!$G$7*(1+E$4)/($B7-E$4)/(1+$B7)^4.5+Assumptions!$C$15)/Assumptions!$C$10 -> 49.226052 | F7: =(SUMPRODUCT(DCF!$C$7:$G$7,1/(1+$B7)^{0.5,1.5,2.5,3.5,4.5})+DCF!$G$7*(1+F$4)/($B7-F$4)/(1+$B7)^4.5+Assumptions!$C$15)/Assumptions!$C$10 -> 50.933729
B8: 0.135 | C8: =(SUMPRODUCT(DCF!$C$7:$G$7,1/(1+$B8)^{0.5,1.5,2.5,3.5,4.5})+DCF!$G$7*(1+C$4)/($B8-C$4)/(1+$B8)^4.5+Assumptions!$C$15)/Assumptions!$C$10 -> 42.939389 | D8: =(SUMPRODUCT(DCF!$C$7:$G$7,1/(1+$B8)^{0.5,1.5,2.5,3.5,4.5})+DCF!$G$7*(1+D$4)/($B8-D$4)/(1+$B8)^4.5+Assumptions!$C$15)/Assumptions!$C$10 -> 44.058388 | E8: =(SUMPRODUCT(DCF!$C$7:$G$7,1/(1+$B8)^{0.5,1.5,2.5,3.5,4.5})+DCF!$G$7*(1+E$4)/($B8-E$4)/(1+$B8)^4.5+Assumptions!$C$15)/Assumptions!$C$10 -> 45.283959 | F8: =(SUMPRODUCT(DCF!$C$7:$G$7,1/(1+$B8)^{0.5,1.5,2.5,3.5,4.5})+DCF!$G$7*(1+F$4)/($B8-F$4)/(1+$B8)^4.5+Assumptions!$C$15)/Assumptions!$C$10 -> 46.632086
B9: 0.14 | C9: =(SUMPRODUCT(DCF!$C$7:$G$7,1/(1+$B9)^{0.5,1.5,2.5,3.5,4.5})+DCF!$G$7*(1+C$4)/($B9-C$4)/(1+$B9)^4.5+Assumptions!$C$15)/Assumptions!$C$10 -> 41.472245 | D9: =(SUMPRODUCT(DCF!$C$7:$G$7,1/(1+$B9)^{0.5,1.5,2.5,3.5,4.5})+DCF!$G$7*(1+D$4)/($B9-D$4)/(1+$B9)^4.5+Assumptions!$C$15)/Assumptions!$C$10 -> 42.482334 | E9: =(SUMPRODUCT(DCF!$C$7:$G$7,1/(1+$B9)^{0.5,1.5,2.5,3.5,4.5})+DCF!$G$7*(1+E$4)/($B9-E$4)/(1+$B9)^4.5+Assumptions!$C$15)/Assumptions!$C$10 -> 43.584249 | F9: =(SUMPRODUCT(DCF!$C$7:$G$7,1/(1+$B9)^{0.5,1.5,2.5,3.5,4.5})+DCF!$G$7*(1+F$4)/($B9-F$4)/(1+$B9)^4.5+Assumptions!$C$15)/Assumptions!$C$10 -> 44.791109
B10: 0.15 | C10: =(SUMPRODUCT(DCF!$C$7:$G$7,1/(1+$B10)^{0.5,1.5,2.5,3.5,4.5})+DCF!$G$7*(1+C$4)/($B10-C$4)/(1+$B10)^4.5+Assumptions!$C$15)/Assumptions!$C$10 -> 38.881002 | D10: =(SUMPRODUCT(DCF!$C$7:$G$7,1/(1+$B10)^{0.5,1.5,2.5,3.5,4.5})+DCF!$G$7*(1+D$4)/($B10-D$4)/(1+$B10)^4.5+Assumptions!$C$15)/Assumptions!$C$10 -> 39.712976 | E10: =(SUMPRODUCT(DCF!$C$7:$G$7,1/(1+$B10)^{0.5,1.5,2.5,3.5,4.5})+DCF!$G$7*(1+E$4)/($B10-E$4)/(1+$B10)^4.5+Assumptions!$C$15)/Assumptions!$C$10 -> 40.614282 | F10: =(SUMPRODUCT(DCF!$C$7:$G$7,1/(1+$B10)^{0.5,1.5,2.5,3.5,4.5})+DCF!$G$7*(1+F$4)/($B10-F$4)/(1+$B10)^4.5+Assumptions!$C$15)/Assumptions!$C$10 -> 41.593962
B11: 0.16 | C11: =(SUMPRODUCT(DCF!$C$7:$G$7,1/(1+$B11)^{0.5,1.5,2.5,3.5,4.5})+DCF!$G$7*(1+C$4)/($B11-C$4)/(1+$B11)^4.5+Assumptions!$C$15)/Assumptions!$C$10 -> 36.665282 | D11: =(SUMPRODUCT(DCF!$C$7:$G$7,1/(1+$B11)^{0.5,1.5,2.5,3.5,4.5})+DCF!$G$7*(1+D$4)/($B11-D$4)/(1+$B11)^4.5+Assumptions!$C$15)/Assumptions!$C$10 -> 37.359252 | E11: =(SUMPRODUCT(DCF!$C$7:$G$7,1/(1+$B11)^{0.5,1.5,2.5,3.5,4.5})+DCF!$G$7*(1+E$4)/($B11-E$4)/(1+$B11)^4.5+Assumptions!$C$15)/Assumptions!$C$10 -> 38.106605 | F11: =(SUMPRODUCT(DCF!$C$7:$G$7,1/(1+$B11)^{0.5,1.5,2.5,3.5,4.5})+DCF!$G$7*(1+F$4)/($B11-F$4)/(1+$B11)^4.5+Assumptions!$C$15)/Assumptions!$C$10 -> 38.913746
B14: Formule : somme des FCF actualisés (convention mid-year) sur la trajectoire de l'onglet DCF + valeur terminale (Gordon growth) au couple (WACC, g), plus trésorerie nette, divisé par le nombre d'actions.

Sheet Market Gap
B2: Lecture de l'écart DCF / marché
B4: Ce que capture le DCF (onglet DCF) | I4: Valeur implicite par action | J4: =DCF!C21 -> 45.283959
B5: Flux de l'activité véhicules électriques et stockage d'énergie telle qu'elle existe aujourd'hui, projetée sur 5 ans puis en valeur terminale (croissance 3 %). | I5: Cours de marche actuel | J5: =DCF!C22 -> 379.26
B8: Ce que la capitalisation boursière intègre en plus
B9: - Robotaxi / Full Self-Driving : licence logicielle à marge quasi-pure si le déploiement réussit (aucun flux encore dans les comptes).
B10: - Optimus (robot humanoïde) : relais de croissance annoncé par la direction, hors des revenus actuels.
B11: - Stockage d'énergie (Megapack) : segment en forte croissance mais encore minoritaire dans le chiffre d'affaires total.
B12: - Prime d'exécution/attentes : le marché valorise Tesla avec un multiple proche de 100x l'EBITDA actuel (voir DCF!C25), contre environ 9x pour la valeur implicite du DCF (DCF!C24), un écart qui ne se retrouve sur aucun constructeur automobile traditionnel.
B15: Conclusion de l'exercice
B16: Un DCF classique sur les flux actuels ne peut pas, à lui seul, justifier le cours de Tesla : c'est un résultat attendu et documenté par de nombreux analystes sell-side, pas une erreur de modélisation. L'exercice a ici une valeur méthodologique : savoir construire un DCF rigoureux ET savoir identifier explicitement ce qu'il ne capture pas, plutôt que de forcer les hypothèses pour recoller au cours de marché.

Sheet Checks
B2: Contrôles de cohérence - Tesla
B5: Contrôle | D5: Résultat
B6: Croissance terminale < WACC (sinon valeur terminale indéfinie) | D6: =IF(Assumptions!C24<Assumptions!C23,"OK","A VERIFIER") -> OK
B7: Toutes les marges de FCF projetées sont strictement positives | D7: =IF(MIN(Assumptions!C30:G30)>0,"OK","A VERIFIER") -> OK
B8: EV recalculée (somme VA FCF + VA valeur terminale) = DCF!C17 | D8: =IF(ROUND(DCF!C12+DCF!C15-DCF!C17,1)=0,"OK","A VERIFIER") -> OK
B9: Valeur des fonds propres (EV + trésorerie nette) = DCF!C19 | D9: =IF(ROUND(DCF!C17+DCF!C18-DCF!C19,1)=0,"OK","A VERIFIER") -> OK
B10: Actions × cours cohérent avec la capitalisation (écart < 6 %, cf. note sur les bases de calcul) | D10: =IF(ABS(Assumptions!C10*Assumptions!C11/Assumptions!C12-1)<0.06,"OK","A VERIFIER") -> OK
B11: Multiple de sortie implicite calculable et positif (contrôle interne ; pas de comparable externe sourcé ici) | D11: =IF(DCF!C35>0,"OK","A VERIFIER") -> OK
B12: Synthèse | C12: =IF(COUNTIF(D6:D11,"OK")=6,"Tous les contrôles sont OK","Au moins un contrôle à vérifier") -> Tous les contrôles sont OK
B15: Note : ces contrôles vérifient la cohérence interne du modèle (pas d'erreur de construction), pas la justesse des hypothèses elles-mêmes.
